danton-1.5.8.dist-info/LICENSE
danton-1.5.8.dist-info/top_level.txt
danton-1.5.8.dist-info/COPYING.LESSER
danton-1.5.8.dist-info/WHEEL
danton-1.5.8.dist-info/RECORD
danton-1.5.8.dist-info/METADATA
danton-1.5.8.dist-info/entry_points.txt
danton/danton.abi3.so
danton/__init__.py
danton/__main__.py
danton/data/geoid/egm96.png
danton/data/pdf/CT14nlo_0000.dat
danton/data/pdf/NNPDF31sx_nlo_as_0118_LHCb_nf_6_0000.dat
danton/data/pdf/HERAPDF15NLO_EIG_0000.dat
danton/data/cs/CMS11.txt
danton/data/cs/BGR18.txt
danton/data/materials/default.toml
