Metadata-Version: 2.1
Name: danton
Version: 1.5.8
Summary: DecAyiNg Taus frOm Neutrinos (Danton).
Author-email: Valentin Niess <valentin.niess@gmail.com>
License: LGPLv3
Project-URL: source, https://github.com/niess/danton
Keywords: neutrino,tau,Monte Carlo,backward
Classifier: Intended Audience :: Science/Research
Classifier: Topic :: Scientific/Engineering :: Physics
Requires-Python: >=3.7.0
License-File: LICENSE
License-File: COPYING.LESSER
Requires-Dist: numpy >=1.6.0
Requires-Dist: tomli ; python_version < "3.11"
